pyedi830/EDI2CSV.py
pyedi830/EDI2HTML.py
pyedi830/EDI2PDF.py
pyedi830/EDIParser.py
pyedi830/EDIParserDF.py
pyedi830/__init__ copy.py
pyedi830/__init__.py
pyedi830/debug.py
pyedi830/hint.py
pyedi830/supported_formats copy.py
pyedi830/supported_formats.py
pyedi830/formats/810.json
pyedi830/formats/830.json
pyedi830/formats/830_Forecast.json
pyedi830/formats/830_Forecast_v1.json
pyedi830/formats/ST.json
pyedi830/template/830_Forecast.html
pyedi830/template/layout.html
pyedi830-1.5.1.dist-info/LICENSE
pyedi830-1.5.1.dist-info/METADATA
pyedi830-1.5.1.dist-info/WHEEL
pyedi830-1.5.1.dist-info/top_level.txt
pyedi830-1.5.1.dist-info/RECORD
