Metadata-Version: 2.1
Name: pyedi830
Version: 1.5.1
Summary: EDI 830 parser/converter
Home-page: https://github.com/dev0088/pyedi830
Author: Ninja Dev
Author-email: ninjadev999@gmail.com
License: MIT
Keywords: x12 edi 830 csv pdf html
Classifier: Development Status :: 3 - Alpha
Classifier: Environment :: Plugins
Classifier: Intended Audience :: Developers
Classifier: Intended Audience :: Healthcare Industry
Classifier: Intended Audience :: System Administrators
Classifier: License :: OSI Approved :: MIT License
Classifier: Topic :: Office/Business
Classifier: Topic :: Text Processing
License-File: LICENSE
Requires-Dist: colorama
Requires-Dist: pandas
Requires-Dist: jinja2
Requires-Dist: weasyprint
